avsim2D/__init__.py
avsim2D/__main__.py
avsim2D/avsim2D.py
avsim2D/config.yml
avsim2D/human.py
avsim2D/main.py
avsim2D/vehicule.py
avsim2D/world.py
avsim2D/Images/human.png
avsim2D/Images/human_back.png
avsim2D/Images/ping.png
avsim2D/Images/vehicule_parts/blinkleft.png
avsim2D/Images/vehicule_parts/blinkright.png
avsim2D/Images/vehicule_parts/highbeam.png
avsim2D/Images/vehicule_parts/lowbeam.png
avsim2D/Images/vehicule_parts/nolights.png
avsim2D/Images/vehicules/car_blue.png
avsim2D/Images/vehicules/car_blue_icon.png
avsim2D/Images/vehicules/car_blue_resize.png
avsim2D/tiled/Arthur.tmx
avsim2D/tiled/Building.png
avsim2D/tiled/Building_CPE
avsim2D/tiled/CPE.png
avsim2D/tiled/CPE.tmx
avsim2D/tiled/CPE_2.tmx
avsim2D/tiled/CPE_3.tmx
avsim2D/tiled/Cars_final.png
avsim2D/tiled/LICENSE
avsim2D/tiled/NY.tmx
avsim2D/tiled/NY_8px.tmx
avsim2D/tiled/Objects.png
avsim2D/tiled/Sidewalk_dark.png
avsim2D/tiled/Street.png
avsim2D/tiled/Street_mini.png
avsim2D/tiled/Street_mini.tsx
avsim2D/tiled/arbre1.png
avsim2D/tiled/arbre2.png
avsim2D/tiled/batiment_CPE
avsim2D/tiled/big_mini_tiles.tmx
avsim2D/tiled/big_mini_tiles_v2.tmx
avsim2D/tiled/building2.png
avsim2D/tiled/building3.png
avsim2D/tiled/building4.png
avsim2D/tiled/fontaine.png
avsim2D/tiled/gazon.png
avsim2D/tiled/goudron.png
avsim2D/tiled/grande_map.tmx
avsim2D/tiled/grande_map1.tmx
avsim2D/tiled/grande_map_marquage.tmx
avsim2D/tiled/grande_map_marquage1.tmx
avsim2D/tiled/grande_map_marquage2.tmx
avsim2D/tiled/grande_map_test.tmx
avsim2D/tiled/grande_map_test_norme.tmx
avsim2D/tiled/logo_CPE.tsx
avsim2D/tiled/maison2.png
avsim2D/tiled/maison3.png
avsim2D/tiled/maison4.png
avsim2D/tiled/maison5.png
avsim2D/tiled/maison6.png
avsim2D/tiled/maison7.png
avsim2D/tiled/maison8.png
avsim2D/tiled/maison_orange.png
avsim2D/tiled/maison_orange2.png
avsim2D/tiled/map_large.tmx
avsim2D/tiled/mini_tiles.tmx
avsim2D/tiled/pave.png
avsim2D/tiled/piste_essai.tmx
avsim2D/tiled/preview(1).jpg
avsim2D/tiled/preview.jpg
avsim2D-0.1.9.dist-info/LICENSE
avsim2D-0.1.9.dist-info/METADATA
avsim2D-0.1.9.dist-info/WHEEL
avsim2D-0.1.9.dist-info/top_level.txt
avsim2D-0.1.9.dist-info/RECORD
