Metadata-Version: 2.1
Name: avsim2D
Version: 0.1.9
Summary: A simple 2D autonomous vehicule simulator with CAN drive-by-wire
Home-page: https://gitlab.com/m0rph03nix/autonomous_vehicule_simulator
Author: Raphael LEBER
License: UNKNOWN
Platform: UNKNOWN
Classifier: Programming Language :: Python :: 3
Classifier: License :: OSI Approved :: MIT License
Classifier: Operating System :: POSIX :: Linux
Requires-Python: >=3.6
Requires-Dist: pygame (>=1.9.6)
Requires-Dist: pylint (>=2.4.4)
Requires-Dist: python-can (>=3.2.1a0)
Requires-Dist: PyTMX (>=3.21.7)
Requires-Dist: PyYAML (>=5.3)
